mali.py
simple_mali_pkg-0.1.0.data/data/mali.py
simple_mali_pkg-0.1.0.dist-info/METADATA
simple_mali_pkg-0.1.0.dist-info/WHEEL
simple_mali_pkg-0.1.0.dist-info/top_level.txt
simple_mali_pkg-0.1.0.dist-info/RECORD
